markitdown_docx_image_plugin/__about__.py
markitdown_docx_image_plugin/__init__.py
markitdown_docx_image_plugin/_plugin.py
markitdown_docx_image_plugin-0.3.0.dist-info/METADATA
markitdown_docx_image_plugin-0.3.0.dist-info/WHEEL
markitdown_docx_image_plugin-0.3.0.dist-info/entry_points.txt
markitdown_docx_image_plugin-0.3.0.dist-info/RECORD
