Metadata-Version: 2.4
Name: markitdown-docx-image-plugin
Version: 0.3.0
Summary: 将Word文档中的图片提取到目录中，并在Markdown中使用相对路径引用
Project-URL: Documentation, https://github.com/microsoft/markitdown#readme
Project-URL: Source, https://github.com/microsoft/markitdown
Author: Fengyun
License-Expression: MIT
Keywords: docx,image,markitdown,plugin
Classifier: Development Status :: 4 - Beta
Classifier: Programming Language :: Python
Classifier: Programming Language :: Python :: 3.10
Classifier: Programming Language :: Python :: 3.11
Classifier: Programming Language :: Python :: 3.12
Classifier: Programming Language :: Python :: 3.13
Requires-Python: >=3.9
Requires-Dist: beautifulsoup4
Requires-Dist: mammoth
Requires-Dist: markdownify
Requires-Dist: markitdown>=0.0.2
